moka_py-0.2.1.dist-info/METADATA
moka_py-0.2.1.dist-info/WHEEL
moka_py-0.2.1.dist-info/licenses/LICENSE
moka_py/__init__.py
moka_py/__init__.pyi
moka_py/moka_py.pypy39-pp73-aarch64-linux-gnu.so
moka_py/py.typed
moka_py-0.2.1.dist-info/RECORD
