Metadata-Version: 2.4
Name: moka-py
Version: 0.2.1
Classifier: Programming Language :: Python :: 3.9
Classifier: Programming Language :: Python :: 3.10
Classifier: Programming Language :: Python :: 3.11
Classifier: Programming Language :: Python :: 3.12
Classifier: Programming Language :: Python :: 3.13
Classifier: Programming Language :: Python :: 3.14
Classifier: Typing :: Typed
Classifier: Programming Language :: Rust
Classifier: Programming Language :: Python :: Implementation :: CPython
Classifier: Programming Language :: Python :: Implementation :: PyPy
License-File: LICENSE
Summary: A high performance caching library for Python written in Rust
Requires-Python: >=3.9
Project-URL: Homepage, https://github.com/deliro/moka-py
Project-URL: Repository, https://github.com/deliro/moka-py
Project-URL: Issues, https://github.com/deliro/moka-py/issues
